{"BasicSettingController":{"Data":{"ProgramToRun":"D:\\Assignments\\semester_2\\oop\\lab_5\\Debug\\lab_5.exe","OptionalWorkingDirectory":"D:\\Assignments\\semester_2\\oop\\lab_5\\lab_5\\","Arguments":"","CompileBeforeRunning":true,"OptimizedBuild":false},"IsSelectedByProjectPath":{"lab_5\\lab_5.vcxproj":true}},"FilterSettingController":{"AdditionalSourcePatterns":[],"AdditionalModulePatterns":[],"ExcludedSourcePatterns":[{"Value":null}],"ExcludedModulePatterns":[],"UnifiedDiffs":[]},"ImportExportSettingController":{"Exports":[],"InputCoverages":[],"CoverChildrenProcesses":false,"AggregateByFile":true},"MiscellaneousSettingController":{"OptionalConfigFile":null,"LogTypeValue":0,"ContinueAfterCppExceptions":false}}